ml_determination/__init__.py
ml_determination/data.py
ml_determination/get_monolingual_translations.py
ml_determination/get_segment_scores.py
ml_determination/model.py
ml_determination/predict_matrix_language.py
ml_determination-1.0.1.dist-info/LICENSE
ml_determination-1.0.1.dist-info/METADATA
ml_determination-1.0.1.dist-info/WHEEL
ml_determination-1.0.1.dist-info/top_level.txt
ml_determination-1.0.1.dist-info/RECORD
