Metadata-Version: 2.1
Name: ml_determination
Version: 1.0.1
Summary: A package for determining the matrix language in bilingual sentences.
Author: Olga Iakovenko
Classifier: Programming Language :: Python :: 3
License-File: LICENSE
Requires-Dist: spacy
Requires-Dist: numpy
Requires-Dist: torch
Requires-Dist: transformers
